selenium_pom
