Metadata-Version: 1.1
Name: selenium-pom
Version: 0.1.2
Summary: Page Object Model for Selenium
Home-page: https://github.com/Presslabs/selenium-pom
Author: Presslabs SRL
Author-email: ping@presslabs.com
License: LICENSE
Platform: UNKNOWN
Classifier: Development Status :: 2 - Pre-Alpha
Classifier: Intended Audience :: Developers
Classifier: Intended Audience :: Developers
Classifier: License :: OSI Approved :: Apache Software License
Classifier: Operating System :: MacOS :: MacOS X
Classifier: Operating System :: Microsoft :: Windows
Classifier: Operating System :: POSIX
Classifier: Topic :: Software Development :: Libraries
Classifier: Topic :: Software Development :: Testing
